{
	"id": "579e3d53-bf7a-4ad3-aefd-5865e2e51bd4",
	"name": "Final Project Environment",
	"values": [
		{
			"key": "url",
			"value": "https://dev-appservice-proj3.azurewebsites.net/api",
			"enabled": true
		},
		{
			"key": "id",
			"value": "99999",
			"enabled": true
		},
		{
			"key": "firstName",
			"value": "\"Nsikan\"",
			"enabled": true
		},
		{
			"key": "lastName",
			"value": "\"Udoyen\"",
			"enabled": true
		}
	],
	"_postman_variable_scope": "environment",
	"_postman_exported_at": "2020-11-11T03:48:26.606Z",
	"_postman_exported_using": "Postman/7.34.0"
}